cnlunar/__init__.py
cnlunar/config.py
cnlunar/demo.py
cnlunar/holidays.py
cnlunar/lunar.py
cnlunar/solar24.py
cnlunar/tools.py
cnlunar-0.2.1.dist-info/licenses/LICENSE
cnlunar-0.2.1.dist-info/METADATA
cnlunar-0.2.1.dist-info/WHEEL
cnlunar-0.2.1.dist-info/top_level.txt
cnlunar-0.2.1.dist-info/RECORD
