Metadata-Version: 2.4
Name: cnlunar
Version: 0.2.1
Summary: 农历，中国农历历法项目，无需数据库环境，以《钦定协纪辨方书》为核心的python3 农历、黄历、二十四节气、节假日、星次、每日凶煞、每日值神、农历建除十二神、农历每日宜忌、彭祖百忌、每日五行、二十八星宿、天干地支、农历生辰八字、时辰凶吉等开源项目。
Home-page: https://github.com/OPN48/cnLunar
Author: cuba3
Author-email: opn48 <cuba3@163.com>
License: MIT License
Project-URL: Homepage, https://github.com/opn48/cnlunar
Project-URL: Repository, https://github.com/opn48/cnlunar.git
Keywords: lunar,chinese lunar,cnlunar,chinese-lunar-calendar,lunarcalendar,calendar
License-File: LICENSE
Dynamic: author
Dynamic: home-page
Dynamic: license-file
